stackit/lbapplication/__init__.py
stackit/lbapplication/api/__init__.py
stackit/lbapplication/api/default_api.py
stackit/lbapplication/api_client.py
stackit/lbapplication/api_response.py
stackit/lbapplication/configuration.py
stackit/lbapplication/exceptions.py
stackit/lbapplication/models/__init__.py
stackit/lbapplication/models/active_health_check.py
stackit/lbapplication/models/certificate_config.py
stackit/lbapplication/models/cookie_persistence.py
stackit/lbapplication/models/create_credentials_payload.py
stackit/lbapplication/models/create_credentials_response.py
stackit/lbapplication/models/create_load_balancer_payload.py
stackit/lbapplication/models/credentials_response.py
stackit/lbapplication/models/get_credentials_response.py
stackit/lbapplication/models/get_quota_response.py
stackit/lbapplication/models/get_service_status_response.py
stackit/lbapplication/models/google_protobuf_any.py
stackit/lbapplication/models/header.py
stackit/lbapplication/models/http_config.py
stackit/lbapplication/models/http_health_checks.py
stackit/lbapplication/models/list_credentials_response.py
stackit/lbapplication/models/list_load_balancers_response.py
stackit/lbapplication/models/list_plans_response.py
stackit/lbapplication/models/listener.py
stackit/lbapplication/models/load_balancer.py
stackit/lbapplication/models/load_balancer_error.py
stackit/lbapplication/models/load_balancer_options.py
stackit/lbapplication/models/loadbalancer_option_access_control.py
stackit/lbapplication/models/loadbalancer_option_logs.py
stackit/lbapplication/models/loadbalancer_option_metrics.py
stackit/lbapplication/models/loadbalancer_option_observability.py
stackit/lbapplication/models/matcher.py
stackit/lbapplication/models/network.py
stackit/lbapplication/models/plan_details.py
stackit/lbapplication/models/protocol_options_https.py
stackit/lbapplication/models/query_parameters.py
stackit/lbapplication/models/rule.py
stackit/lbapplication/models/status.py
stackit_lbapplication-0.4.0.dist-info/LICENSE.md
stackit_lbapplication-0.4.0.dist-info/METADATA
stackit_lbapplication-0.4.0.dist-info/NOTICE.txt
stackit_lbapplication-0.4.0.dist-info/WHEEL
stackit_lbapplication-0.4.0.dist-info/RECORD
